AsEasyAsCache/__init__.py
AsEasyAsCache/abstractClasses.py
AsEasyAsCache/clustering.py
AsEasyAsCache/matrix.py
AsEasyAsCache/sgd.py
AsEasyAsCache/testClustering.py
AsEasyAsCache/testMatrix.py
AsEasyAsCache/testSGD.py
AsEasyAsCache/testVector.py
AsEasyAsCache/vector.py
AsEasyAsCache-0.0.1.dist-info/METADATA
AsEasyAsCache-0.0.1.dist-info/WHEEL
AsEasyAsCache-0.0.1.dist-info/top_level.txt
AsEasyAsCache-0.0.1.dist-info/RECORD
